Metadata-Version: 2.1
Name: triedict
Version: 1.1.1
Summary: 基于字典树的匹配
Home-page: https://github.com/vegaviazhang/triedict
Author: vegaviazhang
Author-email: vegaviazhang@gmail.com
Maintainer: vega
Maintainer-email: vegaviazhang@gmail.com
License: BSD License
Platform: all
Classifier: Development Status :: 4 - Beta
Classifier: Operating System :: OS Independent
Classifier: Intended Audience :: Developers
Classifier: License :: OSI Approved :: BSD License
Classifier: Programming Language :: Python :: 3
Classifier: Programming Language :: Python :: 3.6
Classifier: Programming Language :: Python :: 3.7
Classifier: Programming Language :: Python :: 3.8
Classifier: Topic :: Software Development :: Libraries
